<?xml version="1.0" encoding="UTF-8"?>
<risks
        xmlns="http://www.witsml.org/schemas/131"
        xmlns:xsi="http://www.w3.org/2001/XMLSchema-instance"
        xsi:schemaLocation="http://www.witsml.org/schemas/131  ../obj_risk.xsd"
        version="1.3.1.1">
    <risk uidWell="%uidWell%" uidWellbore="%uidWellbore%" uid="">
        <nameWell/>
        <nameWellbore/>
        <name/>
        <objectReference object="" uidRef=""/>
        <type/>
        <category/>
        <subCategory/>
        <extendCategory/>
        <affectedPersonnel/>
        <dTimStart/>
        <dTimEnd/>
        <mdHoleStart uom=""/>
        <mdHoleEnd uom=""/>
        <tvdHoleStart uom=""/>
        <tvdHoleEnd uom=""/>
        <diaHole uom=""/>
        <severityLevel/>
        <probabilityLevel/>
        <summary/>
        <details/>
        <identification/>
        <mitigation/>
    </risk>
</risks>

