<?xml version="1.0" encoding="UTF-8"?>
<rigs
        xmlns="http://www.witsml.org/schemas/131"
        xmlns:xsi="http://www.w3.org/2001/XMLSchema-instance"
        xsi:schemaLocation="http://www.witsml.org/schemas/131  ../obj_rig.xsd"
        version="1.3.1.1">
    <rig uidWell="%uidWell%" uidWellbore="%uidWellbore%" uid="">
        <nameWell/>
        <nameWellbore/>
        <name/>
        <owner/>
        <typeRig/>
        <manufacturer/>
        <yearEntService/>
        <classRig/>
        <approvals/>
        <registration/>
        <telNumber/>
        <faxNumber/>
        <emailAddress/>
        <nameContact/>
        <ratingDrillDepth uom=""/>
        <ratingWaterDepth uom=""/>
        <isOffshore/>
        <airGap uom=""/>
        <dTimStartOp/>
        <dTimEndOp/>
        <bop>
            <manufacturer/>
            <model/>
            <dTimInstall/>
            <dTimRemove/>
            <nameTag>
                <name/>
                <numberingScheme/>
                <technology/>
                <location/>
                <installationDate/>
                <installationCompany/>
                <mountingCode/>
                <comment/>
            </nameTag>
            <typeConnectionBop/>
            <sizeConnectionBop uom=""/>
            <presBopRating uom=""/>
            <sizeBopSys uom=""/>
            <rotBop/>
            <idBoosterLine uom=""/>
            <odBoosterLine uom=""/>
            <lenBoosterLine uom=""/>
            <idSurfLine uom=""/>
            <odSurfLine uom=""/>
            <lenSurfLine uom=""/>
            <idChkLine uom=""/>
            <odChkLine uom=""/>
            <lenChkLine uom=""/>
            <idKillLine uom=""/>
            <odKillLine uom=""/>
            <lenKillLine uom=""/>
            <bopComponent uid="">
                <typeBopComp/>
                <descComp/>
                <idPassThru uom=""/>
                <presWork uom=""/>
                <diaCloseMn uom=""/>
                <diaCloseMx uom=""/>
                <nomenclature/>
                <isVariable/>
            </bopComponent>
            <typeDiverter/>
            <diaDiverter uom=""/>
            <presWorkDiverter uom=""/>
            <accumulator/>
            <capAccFluid uom=""/>
            <presAccPreCharge uom=""/>
            <volAccPreCharge uom=""/>
            <presAccOpRating uom=""/>
            <typeControlManifold/>
            <descControlManifold/>
            <typeChokeManifold/>
            <presChokeManifold uom=""/>
        </bop>
        <pit uid="">
            <index/>
            <dTimInstall/>
            <dTimRemove/>
            <capMx uom=""/>
            <owner/>
            <typePit/>
            <isActive/>
            <nameTag>
                <name/>
                <numberingScheme/>
                <technology/>
                <location/>
                <installationDate/>
                <installationCompany/>
                <mountingCode/>
                <comment/>
            </nameTag>
        </pit>
        <pump uid="">
            <index/>
            <manufacturer/>
            <model/>
            <dTimInstall/>
            <dTimRemove/>
            <owner/>
            <typePump/>
            <numCyl/>
            <odRod uom=""/>
            <idLiner uom=""/>
            <pumpAction/>
            <eff uom=""/>
            <lenStroke uom=""/>
            <presMx uom=""/>
            <powHydMx uom=""/>
            <spmMx uom=""/>
            <displacement uom=""/>
            <presDamp uom=""/>
            <volDamp uom=""/>
            <powMechMx uom=""/>
            <nameTag>
                <name/>
                <numberingScheme/>
                <technology/>
                <location/>
                <installationDate/>
                <installationCompany/>
                <mountingCode/>
                <comment/>
            </nameTag>
        </pump>
        <shaker uid="">
            <name/>
            <manufacturer/>
            <model/>
            <dTimInstall/>
            <dTimRemove/>
            <type/>
            <locationShaker/>
            <numDecks/>
            <numCascLevel/>
            <mudCleaner/>
            <capFlow uom=""/>
            <owner/>
            <sizeMeshMn uom=""/>
            <nameTag>
                <name/>
                <numberingScheme/>
                <technology/>
                <location/>
                <installationDate/>
                <installationCompany/>
                <mountingCode/>
                <comment/>
            </nameTag>
        </shaker>
        <centrifuge uid="">
            <manufacturer/>
            <model/>
            <dTimInstall/>
            <dTimRemove/>
            <type/>
            <capFlow uom=""/>
            <owner/>
            <nameTag>
                <name/>
                <numberingScheme/>
                <technology/>
                <location/>
                <installationDate/>
                <installationCompany/>
                <mountingCode/>
                <comment/>
            </nameTag>
        </centrifuge>
        <hydrocyclone uid="">
            <manufacturer/>
            <model/>
            <dTimInstall/>
            <dTimRemove/>
            <type/>
            <descCone/>
            <owner/>
            <nameTag>
                <name/>
                <numberingScheme/>
                <technology/>
                <location/>
                <installationDate/>
                <installationCompany/>
                <mountingCode/>
                <comment/>
            </nameTag>
        </hydrocyclone>
        <degasser uid="">
            <manufacturer/>
            <model/>
            <dTimInstall/>
            <dTimRemove/>
            <type/>
            <owner/>
            <height uom=""/>
            <len uom=""/>
            <id uom=""/>
            <capFlow uom=""/>
            <areaSeparatorFlow uom=""/>
            <htMudSeal uom=""/>
            <idInlet uom=""/>
            <idVentLine uom=""/>
            <lenVentLine uom=""/>
            <capGasSep uom=""/>
            <capBlowdown uom=""/>
            <presRating uom=""/>
            <tempRating uom=""/>
            <nameTag>
                <name/>
                <numberingScheme/>
                <technology/>
                <location/>
                <installationDate/>
                <installationCompany/>
                <mountingCode/>
                <comment/>
            </nameTag>
        </degasser>
        <surfaceEquipment>
            <description/>
            <presRating uom=""/>
            <typeSurfEquip/>
            <usePumpDischarge/>
            <useStandpipe/>
            <useHose/>
            <useSwivel/>
            <useKelly/>
            <useTopStack/>
            <useInjStack/>
            <useSurfaceIron/>
            <idStandpipe uom=""/>
            <lenStandpipe uom=""/>
            <idHose uom=""/>
            <lenHose uom=""/>
            <idSwivel uom=""/>
            <lenSwivel uom=""/>
            <idKelly uom=""/>
            <lenKelly uom=""/>
            <idSurfaceIron/>
            <lenSurfaceIron/>
            <htSurfaceIron/>
            <idDischargeLine uom=""/>
            <lenDischargeLine uom=""/>
            <ctWrapType/>
            <odReel uom=""/>
            <odCore uom=""/>
            <widReelWrap uom=""/>
            <lenReel uom=""/>
            <injStkUp/>
            <htInjStk uom=""/>
            <umbInside/>
            <odUmbilical uom=""/>
            <lenUmbilical uom=""/>
            <idTopStk uom=""/>
            <htTopStk uom=""/>
            <htFlange uom=""/>
        </surfaceEquipment>
        <numDerricks/>
        <typeDerrick/>
        <ratingDerrick uom=""/>
        <htDerrick uom=""/>
        <ratingHkld uom=""/>
        <capWindDerrick uom=""/>
        <wtBlock uom="">45</wtBlock>
        <ratingBlock uom=""/>
        <numBlockLines/>
        <typeHook/>
        <ratingHook uom=""/>
        <sizeDrillLine uom=""/>
        <typeDrawWorks/>
        <powerDrawWorks uom=""/>
        <ratingDrawWorks uom=""/>
        <motorDrawWorks/>
        <descBrake/>
        <typeSwivel/>
        <ratingSwivel uom=""/>
        <rotSystem/>
        <descRotSystem/>
        <ratingTqRotSys uom=""/>
        <rotSizeOpening uom=""/>
        <ratingRotSystem uom=""/>
        <scrSystem/>
        <pipeHandlingSystem/>
        <capBulkMud uom=""/>
        <capLiquidMud uom=""/>
        <capDrillWater uom=""/>
        <capPotableWater uom=""/>
        <capFuel uom=""/>
        <capBulkCement uom=""/>
        <mainEngine/>
        <generator/>
        <cementUnit/>
        <numBunks/>
        <bunksPerRoom/>
        <numCranes/>
        <numAnch/>
        <moorType/>
        <numGuideTens/>
        <numRiserTens/>
        <varDeckLdMx uom=""/>
        <vdlStorm uom=""/>
        <numThrusters/>
        <azimuthing/>
        <motionCompensationMn uom=""/>
        <motionCompensationMx uom=""/>
        <strokeMotionCompensation uom=""/>
        <riserAngleLimit uom=""/>
        <heaveMx uom=""/>
        <gantry/>
        <flares/>
        <commonData>
            <itemState/>
            <comments/>
        </commonData>
    </rig>
</rigs>